mark_scraper/__init__.py
mark_scraper/__main__.py
mark_scraper/cli.py
mark_scraper/page.py
mark_scraper/scraper.py
mark_scraper-0.3.0.dist-info/METADATA
mark_scraper-0.3.0.dist-info/WHEEL
mark_scraper-0.3.0.dist-info/entry_points.txt
mark_scraper-0.3.0.dist-info/top_level.txt
mark_scraper-0.3.0.dist-info/RECORD
