Metadata-Version: 2.2
Name: mark-scraper
Version: 0.3.0
Summary: Add your description here
Requires-Python: >=3.10
Requires-Dist: asyncio>=3.4.3
Requires-Dist: bs4>=0.0.2
Requires-Dist: click>=8.1.8
Requires-Dist: markdownify>=0.14.1
Requires-Dist: playwright>=1.49.1
